odoo/addons/sale_delivery_state/README.rst
odoo/addons/sale_delivery_state/__init__.py
odoo/addons/sale_delivery_state/__manifest__.py
odoo/addons/sale_delivery_state/demo/sale_demo.xml
odoo/addons/sale_delivery_state/i18n/it.po
odoo/addons/sale_delivery_state/i18n/ja.po
odoo/addons/sale_delivery_state/i18n/sale_delivery_state.pot
odoo/addons/sale_delivery_state/models/__init__.py
odoo/addons/sale_delivery_state/models/sale_order.py
odoo/addons/sale_delivery_state/readme/CONTRIBUTORS.rst
odoo/addons/sale_delivery_state/readme/DESCRIPTION.rst
odoo/addons/sale_delivery_state/static/description/icon.png
odoo/addons/sale_delivery_state/static/description/index.html
odoo/addons/sale_delivery_state/tests/__init__.py
odoo/addons/sale_delivery_state/tests/test_delivery_state.py
odoo/addons/sale_delivery_state/views/sale_order_views.xml
odoo12_addon_sale_delivery_state-12.0.1.0.0.99.dev12.dist-info/METADATA
odoo12_addon_sale_delivery_state-12.0.1.0.0.99.dev12.dist-info/WHEEL
odoo12_addon_sale_delivery_state-12.0.1.0.0.99.dev12.dist-info/top_level.txt
odoo12_addon_sale_delivery_state-12.0.1.0.0.99.dev12.dist-info/RECORD
